stb/__init__.py
stb/__main__.py
stb/__version__.py
stb/config.py
stb/db.py
stb/graph.py
stb/py.typed
stb/run.py
stb/setup.py
stb/update.py
stb/use.py
stb/utils/__init__.py
stb/utils/common.py
stb/utils/dependency_parser.py
stb_mnt-4.9.1.dist-info/entry_points.txt
stb_mnt-4.9.1.dist-info/LICENSE
stb_mnt-4.9.1.dist-info/WHEEL
stb_mnt-4.9.1.dist-info/METADATA
stb_mnt-4.9.1.dist-info/RECORD
