Metadata-Version: 2.1
Name: stb-mnt
Version: 4.9.1
Summary: A universal tool for local microservice management.
Author: Stanislav Zmiev
Author-email: zmievsa@gmail.com
Requires-Python: >=3.8,<4.0
Classifier: Development Status :: 5 - Production/Stable
Classifier: Environment :: Console
Classifier: Programming Language :: Python :: 3
Classifier: Programming Language :: Python :: 3.8
Classifier: Programming Language :: Python :: 3.9
Classifier: Programming Language :: Python :: 3.10
Classifier: Programming Language :: Python :: 3.11
Requires-Dist: PyYAML (>=6.0,<7.0)
Requires-Dist: keyring (>=23.13.1,<24.0.0)
Requires-Dist: platformdirs (>=2.6.2,<3.0.0)
Requires-Dist: pysh (>=3.1.0,<4.0.0)
Requires-Dist: python-dotenv (>=0.21.0,<0.22.0)
Requires-Dist: python-gitlab (>=3.13.0,<4.0.0)
Requires-Dist: requests (>=2.28.2,<3.0.0)
Requires-Dist: tomli (>=2.0.1,<3.0.0)
Requires-Dist: tomlkit (>=0.11.6,<0.12.0)
Requires-Dist: typer[all] (>=0.6.1,<0.7.0)
Requires-Dist: typing-extensions (>=4.3.0,<5.0.0)
